set_proxy-0.2.0.dist-info/METADATA
set_proxy-0.2.0.dist-info/WHEEL
set_proxy-0.2.0.dist-info/entry_points.txt
set_proxy/__init__.py
set_proxy/network.py
set_proxy-0.2.0.dist-info/RECORD
