Metadata-Version: 2.1
Name: set_proxy
Version: 0.2.0
Summary: a network checker and proxy setter
Author-Email: svtter <svtter@qq.com>
License: MIT
Requires-Python: >=3.9
Requires-Dist: requests>=2.32.3
